nii2dcm/__init__.py
nii2dcm/__main__.py
nii2dcm/_version.py
nii2dcm/dcm.py
nii2dcm/dcm_writer.py
nii2dcm/module.py
nii2dcm/nii.py
nii2dcm/run.py
nii2dcm/svr.py
nii2dcm/utils.py
nii2dcm/modules/__init__.py
nii2dcm/modules/common_instance_reference.py
nii2dcm/modules/frame_of_reference.py
nii2dcm/modules/general_acquisition.py
nii2dcm/modules/general_equipment.py
nii2dcm/modules/general_image.py
nii2dcm/modules/general_reference.py
nii2dcm/modules/general_series.py
nii2dcm/modules/general_study.py
nii2dcm/modules/image_pixel.py
nii2dcm/modules/image_plane.py
nii2dcm/modules/mr_image.py
nii2dcm/modules/patient.py
nii2dcm/modules/patient_study.py
nii2dcm/modules/sop_common.py
nii2dcm/modules/voi_lut.py
nii2dcm/test/__init__.py
tests/__init__.py
tests/test_dcm.py
tests/test_dcm_writer.py
tests/test_nii.py
tests/test_run.py
tests/test_version.py
nii2dcm-0.1.6.dist-info/LICENSE
nii2dcm-0.1.6.dist-info/METADATA
nii2dcm-0.1.6.dist-info/WHEEL
nii2dcm-0.1.6.dist-info/entry_points.txt
nii2dcm-0.1.6.dist-info/top_level.txt
nii2dcm-0.1.6.dist-info/RECORD
