Metadata-Version: 2.1
Name: nii2dcm
Version: 0.1.6
Summary: nii2dcm: NIfTI to DICOM creation with Python
Home-page: https://github.com/tomaroberts/nii2dcm
Author: Tom Roberts
Author-email: t.roberts@kcl.ac.uk
License: BSD-3-Clause
Platform: UNKNOWN
Classifier: License :: OSI Approved :: BSD License
Requires-Python: <3.12
License-File: LICENSE
Requires-Dist: numpy==1.23.2
Requires-Dist: matplotlib==3.6.2
Requires-Dist: nibabel==5.0.0
Requires-Dist: pydicom==2.3.0
Requires-Dist: twine==4.0.2
Requires-Dist: dunamai==1.18.0
